{
    "index_patterns": [
        "hn-stories-comments"
    ],
    "template": {
        "mappings": {
            "properties": {
                "story": {
                    "type": "nested",
                    "properties": {
                        "by": {
                            "type": "keyword"
                        },
                        "type": {
                            "type": "keyword"
                        },
                        "url": {
                            "type": "keyword"
                        },
                        "text": {
                            "type": "text"
                        }
                    }
                },
                "comments": {
                    "type": "nested",
                    "properties": {
                        "by": {
                            "type": "keyword"
                        },
                        "type": {
                            "type": "keyword"
                        },
                        "url": {
                            "type": "keyword"
                        },
                        "text": {
                            "type": "text"
                        }
                    }
                }
            }
        }
    }
}